setup.py
zm_dsnd_probability/Binomialdistribution.py
zm_dsnd_probability/Gaussiandistribution.py
zm_dsnd_probability/Generaldistribution.py
zm_dsnd_probability/__init__.py
zm_dsnd_probability.egg-info/PKG-INFO
zm_dsnd_probability.egg-info/SOURCES.txt
zm_dsnd_probability.egg-info/dependency_links.txt
zm_dsnd_probability.egg-info/not-zip-safe
zm_dsnd_probability.egg-info/top_level.txt