Metadata-Version: 1.0
Name: zm-dsnd-probability
Version: 0.1
Summary: Gaussian and Binomial distributions
Home-page: UNKNOWN
Author: Zimei Chen
Author-email: chenzm1106@gmail.com
License: UNKNOWN
Platform: UNKNOWN
